Metadata-Version: 1.1
Name: test-chain
Version: 0.0.1
Summary: This contains unit test automation material, specifically a
Home-page: UNKNOWN
Author: Michael Christenson
Author-email: mochristenson@gmail.com.com
License: UNKNOWN
Platform: UNKNOWN
Classifier: Development Status :: 4 - Beta
Classifier: Intended Audience :: Developers
Classifier: Natural Language :: English
Classifier: License :: Other/Proprietary License
Classifier: Operating System :: POSIX :: Linux
Classifier: Programming Language :: Python
Classifier: Programming Language :: Python :: 3.5
